aa_pytools/__init__.py
aa_pytools/api/__init__.py
aa_pytools/core/__init__.py
aa_pytools/core/logging.py
aa_pytools/decorators/__init__.py
aa_pytools/decorators/safe_execute.py
aa_pytools/execution/__init__.py
aa_pytools/vault/__init__.py
aa_pytools-1.0.0.dist-info/licenses/LICENSE
aa_pytools-1.0.0.dist-info/METADATA
aa_pytools-1.0.0.dist-info/WHEEL
aa_pytools-1.0.0.dist-info/top_level.txt
aa_pytools-1.0.0.dist-info/RECORD
