Metadata-Version: 2.4
Name: aa_pytools
Version: 1.0.0
Summary: This project contains useful tools to work with Automation Anywhere + Python
Author-email: AND3SIL4 <devaul.fs@gmail.com>
Maintainer-email: AND3SIL4 <devaul.fs@gmail.com>
License-Expression: MIT
Project-URL: Homepage, https://github.com/AND3SIL4/aa-pytools
Project-URL: Issues, https://github.com/AND3SIL4/aa-pytools/issues
Keywords: Automation Anywhere,Integration,Python,RPA
Classifier: Operating System :: OS Independent
Classifier: Programming Language :: Python :: 3
Requires-Python: >=3.13
License-File: LICENSE
Dynamic: license-file
